[
  {
    "word": "Bounded",
    "start": 0.0
  },
  {
    "word": "Context:",
    "start": 0.34
  },
  {
    "word": "Estate",
    "start": 1.44
  },
  {
    "word": "Structures",
    "start": 1.68
  },
  {
    "word": "The",
    "start": 2.74
  },
  {
    "word": "spatial",
    "start": 3.22
  },
  {
    "word": "hierarchy",
    "start": 3.72
  },
  {
    "word": "estate_structures_v1",
    "start": 5.0
  },
  {
    "word": "models",
    "start": 6.72
  },
  {
    "word": "the",
    "start": 7.12
  },
  {
    "word": "physical",
    "start": 7.4
  },
  {
    "word": "world:",
    "start": 7.72
  },
  {
    "word": "an",
    "start": 8.6
  },
  {
    "word": "Estate",
    "start": 8.76
  },
  {
    "word": "(a",
    "start": 9.7
  },
  {
    "word": "company's",
    "start": 9.8
  },
  {
    "word": "entire",
    "start": 10.4
  },
  {
    "word": "property",
    "start": 10.76
  },
  {
    "word": "portfolio)",
    "start": 11.3
  },
  {
    "word": "contains",
    "start": 11.96
  },
  {
    "word": "Sites",
    "start": 12.72
  },
  {
    "word": "(individual",
    "start": 13.8
  },
  {
    "word": "buildings",
    "start": 14.06
  },
  {
    "word": "or",
    "start": 14.7
  },
  {
    "word": "facilities),",
    "start": 15.04
  },
  {
    "word": "which",
    "start": 16.16
  },
  {
    "word": "contain",
    "start": 16.38
  },
  {
    "word": "Buildings,",
    "start": 16.76
  },
  {
    "word": "which",
    "start": 17.68
  },
  {
    "word": "contain",
    "start": 17.82
  },
  {
    "word": "Rooms.",
    "start": 18.3
  },
  {
    "word": "But",
    "start": 19.24
  },
  {
    "word": "it",
    "start": 19.4
  },
  {
    "word": "goes",
    "start": 19.54
  },
  {
    "word": "deeper.",
    "start": 19.82
  },
  {
    "word": "SiteTopologyAggregate",
    "start": 21.02
  },
  {
    "word": "manages",
    "start": 22.16
  },
  {
    "word": "spatial",
    "start": 22.84
  },
  {
    "word": "geometry:",
    "start": 23.42
  },
  {
    "word": "site",
    "start": 24.82
  },
  {
    "word": "boundaries",
    "start": 25.02
  },
  {
    "word": "as",
    "start": 25.5
  },
  {
    "word": "GeoJSON",
    "start": 26.0
  },
  {
    "word": "polygons,",
    "start": 26.92
  },
  {
    "word": "building",
    "start": 27.6
  },
  {
    "word": "footprints,",
    "start": 28.2
  },
  {
    "word": "floor",
    "start": 29.04
  },
  {
    "word": "plans",
    "start": 29.48
  },
  {
    "word": "calibrated",
    "start": 30.0
  },
  {
    "word": "to",
    "start": 30.86
  },
  {
    "word": "real-world",
    "start": 31.04
  },
  {
    "word": "coordinates.",
    "start": 31.84
  },
  {
    "word": "MapTile",
    "start": 33.1
  },
  {
    "word": "value",
    "start": 33.54
  },
  {
    "word": "objects",
    "start": 34.0
  },
  {
    "word": "represent",
    "start": 34.52
  },
  {
    "word": "floor",
    "start": 35.26
  },
  {
    "word": "plan",
    "start": 35.68
  },
  {
    "word": "images",
    "start": 36.02
  },
  {
    "word": "with",
    "start": 36.42
  },
  {
    "word": "rotation,",
    "start": 36.9
  },
  {
    "word": "scale,",
    "start": 38.0
  },
  {
    "word": "and",
    "start": 38.3
  },
  {
    "word": "position",
    "start": 38.72
  },
  {
    "word": "transforms.",
    "start": 39.16
  },
  {
    "word": "The",
    "start": 40.5
  },
  {
    "word": "TopologyIndex",
    "start": 40.58
  },
  {
    "word": "provides",
    "start": 41.36
  },
  {
    "word": "spatial",
    "start": 41.76
  },
  {
    "word": "queries:",
    "start": 42.38
  },
  {
    "word": "'Which",
    "start": 43.28
  },
  {
    "word": "rooms",
    "start": 43.52
  },
  {
    "word": "contain",
    "start": 43.9
  },
  {
    "word": "this",
    "start": 44.34
  },
  {
    "word": "point?',",
    "start": 44.64
  },
  {
    "word": "'What's",
    "start": 45.46
  },
  {
    "word": "at",
    "start": 45.62
  },
  {
    "word": "building",
    "start": 45.68
  },
  {
    "word": "Main,",
    "start": 46.0
  },
  {
    "word": "level",
    "start": 46.34
  },
  {
    "word": "2?'",
    "start": 46.34
  },
  {
    "word": "There's",
    "start": 47.64
  },
  {
    "word": "a",
    "start": 47.9
  },
  {
    "word": "full",
    "start": 47.98
  },
  {
    "word": "draft/publish",
    "start": 48.2
  },
  {
    "word": "workflow\u2014topology",
    "start": 49.52
  },
  {
    "word": "changes",
    "start": 50.98
  },
  {
    "word": "are",
    "start": 51.52
  },
  {
    "word": "staged,",
    "start": 51.76
  },
  {
    "word": "validated",
    "start": 52.82
  },
  {
    "word": "for",
    "start": 53.24
  },
  {
    "word": "geometric",
    "start": 53.6
  },
  {
    "word": "correctness",
    "start": 54.08
  },
  {
    "word": "(no",
    "start": 54.92
  },
  {
    "word": "self-intersecting",
    "start": 55.56
  },
  {
    "word": "polygons,",
    "start": 56.58
  },
  {
    "word": "buildings",
    "start": 57.46
  },
  {
    "word": "inside",
    "start": 57.72
  },
  {
    "word": "boundaries),",
    "start": 58.28
  },
  {
    "word": "then",
    "start": 59.44
  },
  {
    "word": "published",
    "start": 59.72
  },
  {
    "word": "atomically.",
    "start": 59.72
  },
  {
    "word": "It's",
    "start": 61.38
  },
  {
    "word": "genuinely",
    "start": 61.56
  },
  {
    "word": "sophisticated",
    "start": 62.0
  },
  {
    "word": "spatial",
    "start": 62.8
  },
  {
    "word": "modelling.",
    "start": 62.8
  },
  {
    "word": "It's",
    "start": 64.6
  },
  {
    "word": "also",
    "start": 64.8
  },
  {
    "word": "where",
    "start": 65.08
  },
  {
    "word": "the",
    "start": 65.34
  },
  {
    "word": "codebase",
    "start": 65.5
  },
  {
    "word": "shows",
    "start": 65.92
  },
  {
    "word": "its",
    "start": 66.24
  },
  {
    "word": "archaeology:",
    "start": 66.52
  },
  {
    "word": "there",
    "start": 67.74
  },
  {
    "word": "are",
    "start": 67.98
  },
  {
    "word": "legacy",
    "start": 68.14
  },
  {
    "word": "GeoJSON",
    "start": 68.56
  },
  {
    "word": "storage",
    "start": 69.62
  },
  {
    "word": "formats,",
    "start": 70.16
  },
  {
    "word": "deprecated",
    "start": 71.2
  },
  {
    "word": "feature",
    "start": 71.72
  },
  {
    "word": "types,",
    "start": 72.06
  },
  {
    "word": "and",
    "start": 72.84
  },
  {
    "word": "a",
    "start": 73.0
  },
  {
    "word": "500-line",
    "start": 73.08
  },
  {
    "word": "glossary",
    "start": 74.06
  },
  {
    "word": "entry",
    "start": 74.64
  },
  {
    "word": "trying",
    "start": 75.04
  },
  {
    "word": "to",
    "start": 75.54
  },
  {
    "word": "explain",
    "start": 75.72
  },
  {
    "word": "the",
    "start": 76.12
  },
  {
    "word": "difference",
    "start": 76.32
  },
  {
    "word": "between",
    "start": 76.62
  },
  {
    "word": "unplacedBuildingMapTile",
    "start": 77.02
  },
  {
    "word": "and",
    "start": 78.68
  },
  {
    "word": "unplacedSiteMapTile.",
    "start": 79.24
  }
]